multi_sum_calc/__init__.py
multi_sum_calc/multicalc.py
multi_sum_calc/sumcalc.py
multi_sum_calc-0.4.dist-info/METADATA
multi_sum_calc-0.4.dist-info/WHEEL
multi_sum_calc-0.4.dist-info/top_level.txt
multi_sum_calc-0.4.dist-info/RECORD
